oomongo.py
oomongo-1.1.2.dist-info/LICENSE
oomongo-1.1.2.dist-info/WHEEL
oomongo-1.1.2.dist-info/METADATA
oomongo-1.1.2.dist-info/RECORD
