Metadata-Version: 2.1
Name: oomongo
Version: 1.1.2
Summary: 一个非常优雅的 MongoDB ODM
Keywords: mongodb,pymongo,motor,oomongo
Author-email: 江南雨上 <lcctoor@outlook.com>
Classifier: License :: OSI Approved :: Apache Software License
Requires-Dist: arts>=2024.7.29
Project-URL: Source, https://github.com/lcctoor/arts/tree/main/arts/oomongo
